czv-0.0.1.dist-info/METADATA
czv-0.0.1.dist-info/WHEEL
czv/__init__.py
czv/__init__.pyi
czv/py.typed
czv/czv.cpython-310-x86_64-linux-gnu.so
czv-0.0.1.dist-info/RECORD
