Metadata-Version: 2.3
Name: czv
Version: 0.0.1
Classifier: Programming Language :: Rust
Classifier: Programming Language :: Python :: Implementation :: CPython
Classifier: Programming Language :: Python :: Implementation :: PyPy
Summary: Python library for performing CSV-related functions for data engineering and analysis.
Author: Mueez Khan
Requires-Python: >=3.8
Project-URL: Source Code, https://github.com/rzmk/czv
